LICENSE
wodoo_rpc/__init__.py
wodoo_rpc/api.py
wodoo_rpc/file_2_odoo.py
wodoo_rpc/helpers.py
wodoo_rpc/importers/__init__.py
wodoo_rpc/importers/import_csv.py
wodoo_rpc/importers/import_data.py
wodoo_rpc/importers/import_product_images.py
wodoo_rpc/importers/import_settings.py
wodoo_rpc/importers/import_translation.py
wodoo_rpc/importers/import_xl.py
wodoo_rpc/login.py
wodoo_rpc/odoo2odoo_mapper.py
wodoo_rpc/odoo_dataset.py
wodoo_rpc-0.0.2.dist-info/LICENSE
wodoo_rpc-0.0.2.dist-info/WHEEL
wodoo_rpc-0.0.2.dist-info/METADATA
wodoo_rpc-0.0.2.dist-info/RECORD
