Metadata-Version: 2.1
Name: wodoo-rpc
Version: 0.0.2
Summary: Helper Functions around OdooRPC
Home-page: https://gitlab.com/joshuader6/wodoo-rpc
License: GPL-3
Keywords: odoorpc,odoo
Author: Joshua Kreuder
Author-email: joshua_kreuder@outlook.com
Requires-Python: >=3.8,<3.11
Classifier: License :: Other/Proprietary License
Classifier: Programming Language :: Python :: 3
Classifier: Programming Language :: Python :: 3.8
Classifier: Programming Language :: Python :: 3.9
Classifier: Programming Language :: Python :: 3.10
Requires-Dist: OdooRPC (>=0.8.0,<0.9.0)
Requires-Dist: openpyxl (>=3.0.10,<4.0.0)
Requires-Dist: pylint-gitlab (>=1.1.0,<2.0.0)
Requires-Dist: python-dotenv (>=0.20.0,<0.21.0)
Requires-Dist: requests (>=2.25.1,<3.0.0)
Requires-Dist: wodoo-datalib (>=0.0.1,<0.0.2)
Project-URL: Repository, https://gitlab.com/joshuader6/wodoo-rpc
